appsignal/__about__.py
appsignal/__init__.py
appsignal/__main__.py
appsignal/_appsignal_platform
appsignal/agent.py
appsignal/binary.py
appsignal/client.py
appsignal/config.py
appsignal/heartbeat.py
appsignal/internal_logger.py
appsignal/metrics.py
appsignal/ndjson.py
appsignal/opentelemetry.py
appsignal/probes.py
appsignal/push_api_key_validator.py
appsignal/py.typed
appsignal/tracing.py
appsignal/transmitter.py
appsignal/check_in/__init__.py
appsignal/check_in/cron.py
appsignal/check_in/event.py
appsignal/check_in/heartbeat.py
appsignal/check_in/scheduler.py
appsignal/cli/__init__.py
appsignal/cli/base.py
appsignal/cli/command.py
appsignal/cli/demo.py
appsignal/cli/diagnose.py
appsignal/cli/exit_error.py
appsignal/cli/install.py
appsignal/cli/version.py
appsignal/resources/cacert.pem
appsignal-1.6.1.dist-info/METADATA
appsignal-1.6.1.dist-info/WHEEL
appsignal-1.6.1.dist-info/entry_points.txt
appsignal-1.6.1.dist-info/licenses/LICENSE
appsignal-1.6.1.dist-info/RECORD
