Metadata-Version: 2.4
Name: appsignal
Version: 1.6.1
Summary: The AppSignal integration for the Python programming language
Project-URL: Documentation, https://docs.appsignal.com/python
Project-URL: Issues, https://github.com/appsignal/appsignal-python/issues
Project-URL: Source, https://github.com/appsignal/appsignal-python
Author-email: Tom de Bruijn <tom@tomdebruijn.com>, Noemi Lapresta <noemi@appsignal.com>
License-File: LICENSE
Classifier: Development Status :: 5 - Production/Stable
Classifier: Programming Language :: Python
Classifier: Programming Language :: Python :: 3.8
Classifier: Programming Language :: Python :: 3.9
Classifier: Programming Language :: Python :: 3.10
Classifier: Programming Language :: Python :: 3.11
Classifier: Programming Language :: Python :: 3.12
Classifier: Programming Language :: Python :: Implementation :: CPython
Classifier: Programming Language :: Python :: Implementation :: PyPy
Requires-Python: >=3.8
Requires-Dist: opentelemetry-api>=1.26.0
Requires-Dist: opentelemetry-exporter-otlp-proto-http
Requires-Dist: opentelemetry-sdk>=1.26.0
Requires-Dist: typing-extensions
